{
  "content": [
    {
      "type": "paragraph",
      "children": [
        {
          "text": ""
        }
      ],
      "align": "center"
    },
    {
      "type": "paragraph",
      "children": [
        {
          "text": "Works Cited"
        }
      ],
      "align": "center"
    },
    {
      "type": "paragraph",
      "children": [
        {
          "text": "Deiss, Heather, and Abigail Bowman. “Apollo 11.” Nasa.Gov, 5 Jan. 2024, www.nasa.gov/mission/apollo-11/. "
        }
      ]
    },
    {
      "type": "paragraph",
      "children": [
        {
          "text": "\nThaler, F., Haug, M., Gewald, H., & Brune, P. (2024). The Context Sets the Tone: A Literature Review on Emotion Recognition from Speech Using AI. In F. Pennarola, J. Pallud, & A. M. Braccini (Eds.), "
        },
        {
          "text": "Technologies for Digital Transformation",
          "italic": true
        },
        {
          "text": " (Vol. 64, pp. 129–143). Springer Nature Switzerland. https://doi.org/10.1007/978-3-031-52120-1_8\n"
        }
      ]
    },
    {
      "type": "paragraph",
      "children": [
        {
          "text": "Dale, Daniel. \"Fact Check: Nine Trump False Claims about Canada | CNN Politics.\" CNN, 12 Mar. 2025, www.cnn.com/2025/03/12/politics/fact-check-trump-canada-claims.\n\n"
        }
      ]
    }
  ],
  "title": "Works Cited",
  "autogenerate": {
    "enabled": false,
    "type": "custom"
  },
  "slug": "works-cited",
  "created_at": "2026-02-25T16:27:50.397Z",
  "created_by": "Miguel-212",
  "updated_at": "2026-02-26T19:08:43.091Z",
  "updated_by": "dt961"
}